[
  {
    "title": "Первый",
    "imgName": "one.png",
    "imgAlt": "one",
    "shows": [
      {
        "time": "05:00",
        "title": "Телеканал 'Доброе утро'"
      },
      {
        "time": "09:00",
        "title": "Новости"
      },
      {
        "time": "09:20",
        "title": "Контрольная закупка"
      },
      {
        "time": "16:00",
        "title": "Мужское / Женское"
      },
      {
        "time": "18:00",
        "title": "Вечерние новости с субтитрами"
      },
      {
        "time": "18:45",
        "title": "Давай поженимся!"
      },
      {
        "time": "19:50",
        "title": "'Пусть говорят' с Андреем Малаховым"
      },
      {
        "time": "21:00",
        "title": "Время"
      },
      {
        "time": "21:25",
        "title": "Мужское / Женское"
      },
      {
        "time": "21:30",
        "title": "Вечерние новости с субтитрами"
      },
      {
        "time": "22:45",
        "title": "Давай поженимся!"
      },
      {
        "time": "22:50",
        "title": "'Пусть говорят' с Андреем Малаховым"
      },
      {
        "time": "23:50",
        "title": "Время"
      }
    ]
  },
  {
    "title": "Пятый канал",
    "imgName": "five.png",
    "imgAlt": "five",
    "shows": [
      {
        "time": "05:00",
        "title": "Телеканал 'Доброе утро'"
      },
      {
        "time": "09:00",
        "title": "Новости"
      },
      {
        "time": "09:20",
        "title": "Контрольная закупка"
      },
      {
        "time": "16:00",
        "title": "Мужское / Женское"
      },
      {
        "time": "18:00",
        "title": "Вечерние новости с субтитрами"
      },
      {
        "time": "18:45",
        "title": "Давай поженимся!"
      },
      {
        "time": "19:50",
        "title": "'Пусть говорят' с Андреем Малаховым"
      },
      {
        "time": "21:00",
        "title": "Время"
      },
      {
        "time": "21:10",
        "title": "Телеканал 'Доброе утро'"
      },
      {
        "time": "21:15",
        "title": "Новости"
      },
      {
        "time": "21:20",
        "title": "Контрольная закупка"
      },
      {
        "time": "21:25",
        "title": "Мужское / Женское"
      },
      {
        "time": "21:30",
        "title": "Вечерние новости с субтитрами"
      },
      {
        "time": "22:45",
        "title": "Давай поженимся!"
      },
      {
        "time": "22:50",
        "title": "'Пусть говорят' с Андреем Малаховым"
      },
      {
        "time": "23:50",
        "title": "Время"
      }
    ]
  },
  {
    "title": "Матч",
    "imgName": "match.jpeg",
    "imgAlt": "match",
    "shows": [
      {
        "time": "05:00",
        "title": "Телеканал 'Доброе утро'"
      },
      {
        "time": "09:00",
        "title": "Новости"
      },
      {
        "time": "09:20",
        "title": "Контрольная закупка"
      },
      {
        "time": "16:00",
        "title": "Мужское / Женское"
      },
      {
        "time": "18:00",
        "title": "Вечерние новости с субтитрами"
      },
      {
        "time": "18:45",
        "title": "Давай поженимся!"
      },
      {
        "time": "19:50",
        "title": "'Пусть говорят' с Андреем Малаховым"
      },
      {
        "time": "21:00",
        "title": "Время"
      },
      {
        "time": "21:10",
        "title": "Телеканал 'Доброе утро'"
      },
      {
        "time": "21:15",
        "title": "Новости"
      },
      {
        "time": "21:20",
        "title": "Контрольная закупка"
      },
      {
        "time": "21:25",
        "title": "Мужское / Женское"
      },
      {
        "time": "21:30",
        "title": "Вечерние новости с субтитрами"
      },
      {
        "time": "22:45",
        "title": "Давай поженимся!"
      },
      {
        "time": "22:50",
        "title": "'Пусть говорят' с Андреем Малаховым"
      },
      {
        "time": "23:50",
        "title": "Время"
      }
    ]
  },
  {
    "title": "НТВ",
    "imgName": "ntv.jpeg",
    "imgAlt": "ntv",
    "shows": [
      {
        "time": "05:00",
        "title": "Телеканал 'Доброе утро'"
      },
      {
        "time": "09:00",
        "title": "Новости"
      },
      {
        "time": "09:20",
        "title": "Контрольная закупка"
      },
      {
        "time": "16:00",
        "title": "Мужское / Женское"
      },
      {
        "time": "18:00",
        "title": "Вечерние новости с субтитрами"
      },
      {
        "time": "18:45",
        "title": "Давай поженимся!"
      },
      {
        "time": "19:50",
        "title": "'Пусть говорят' с Андреем Малаховым"
      },
      {
        "time": "21:00",
        "title": "Время"
      },
      {
        "time": "21:10",
        "title": "Телеканал 'Доброе утро'"
      },
      {
        "time": "22:50",
        "title": "'Пусть говорят' с Андреем Малаховым"
      },
      {
        "time": "23:50",
        "title": "Время"
      }
    ]
  },
  {
    "title": "Россия",
    "imgName": "russia.png",
    "imgAlt": "russia",
    "shows": [
      {
        "time": "05:00",
        "title": "Телеканал 'Доброе утро'"
      },
      {
        "time": "09:00",
        "title": "Новости"
      },
      {
        "time": "09:20",
        "title": "Контрольная закупка"
      },
      {
        "time": "16:00",
        "title": "Мужское / Женское"
      },
      {
        "time": "18:00",
        "title": "Вечерние новости с субтитрами"
      },
      {
        "time": "18:45",
        "title": "Давай поженимся!"
      },
      {
        "time": "19:50",
        "title": "'Пусть говорят' с Андреем Малаховым"
      },
      {
        "time": "21:00",
        "title": "Время"
      },
      {
        "time": "21:10",
        "title": "Телеканал 'Доброе утро'"
      },
      {
        "time": "21:15",
        "title": "Новости"
      },
      {
        "time": "21:20",
        "title": "Контрольная закупка"
      },
      {
        "time": "21:25",
        "title": "Мужское / Женское"
      },
      {
        "time": "21:30",
        "title": "Вечерние новости с субтитрами"
      },
      {
        "time": "22:45",
        "title": "Давай поженимся!"
      },
      {
        "time": "22:50",
        "title": "'Пусть говорят' с Андреем Малаховым"
      },
      {
        "time": "23:50",
        "title": "Время"
      }
    ]
  }
]